djflocash/__init__.py
djflocash/__version__.py
djflocash/apps.py
djflocash/codes.py
djflocash/forms.py
djflocash/managers.py
djflocash/models.py
djflocash/signals.py
djflocash/urls.py
djflocash/utils.py
djflocash/views.py
djflocash/migrations/0001_initial.py
djflocash/migrations/0002_auto_20181023_0403.py
djflocash/migrations/__init__.py
djflocash/test/__init__.py
djflocash/test/factories.py
djflocash/test/mock.py
djflocash-0.1.2.dist-info/METADATA
djflocash-0.1.2.dist-info/RECORD
djflocash-0.1.2.dist-info/WHEEL
djflocash-0.1.2.dist-info/top_level.txt
