Metadata-Version: 2.1
Name: djflocash
Version: 0.1.2
Summary: Using flocash payment gateway interface with Django
Home-page: https://github.com/jurismarches/djflocash
Author: Jurismarches
Author-email: contact@jurismarches.com
License: UNKNOWN
Platform: UNKNOWN
Classifier: Development Status :: 4 - Beta
Classifier: License :: OSI Approved :: GNU Lesser General Public License v3 or later (LGPLv3+)
Classifier: Framework :: Django
Classifier: Intended Audience :: Developers
Classifier: Programming Language :: Python
Classifier: Programming Language :: Python :: 3.4
Classifier: Programming Language :: Python :: 3.5
Classifier: Programming Language :: Python :: 3.6
Requires-Dist: pycountry (>=18.5.26)
Requires-Dist: django (>=1.10)
Requires-Dist: requests (>=2.18.4)
